RDG/RDG.py
RDG/RDG_to_file.py
RDG/__init__.py
RDG/build_RDG_from_sequence.py
RDG/cli.py
RDG/decision_graph.py
RDG/dynamic_build.py
RDG/plot.py
RDG/plot_RDG.py
RDG/sequence_to_RDG.py
tests/__init__.py
tests/test_add_features.py
tests/test_add_remove_edge.py
tests/test_basics.py
tests/test_edgeObj.py
tests/test_get.py
tests/test_inset_orf.py
tests/test_load_graph.py
tests/test_newick.py
tests/test_nodeObj.py
tests/test_read_write.py
tests/test_remove_edge.py
tests/test_sequence_to_RDG.py
tests/test_update_edge.py
RDG-0.1.6.dist-info/LICENSE
RDG-0.1.6.dist-info/METADATA
RDG-0.1.6.dist-info/WHEEL
RDG-0.1.6.dist-info/entry_points.txt
RDG-0.1.6.dist-info/top_level.txt
RDG-0.1.6.dist-info/RECORD
