Metadata-Version: 2.1
Name: RDG
Version: 0.1.6
Summary: A python command-line utility for Ribosome Decision Graph (RDG) generation.
Home-page: https://github.com/jackcurragh/RDG
Author: Jack Tierney
Author-email: jackcurragh@gmail.com
License: MIT license
Keywords: RDG,Ribosome Decision Graph
Classifier: Development Status :: 2 - Pre-Alpha
Classifier: Intended Audience :: Developers
Classifier: License :: OSI Approved :: MIT License
Classifier: Natural Language :: English
Classifier: Programming Language :: Python :: 3
Classifier: Programming Language :: Python :: 3.8
Classifier: Programming Language :: Python :: 3.9
Classifier: Programming Language :: Python :: 3.10
Requires-Python: >=3.8
License-File: LICENSE
Requires-Dist: click ==8.1.7
Requires-Dist: contourpy ==1.2.0
Requires-Dist: cycler ==0.12.1
Requires-Dist: fonttools ==4.47.2
Requires-Dist: iniconfig ==2.0.0
Requires-Dist: kiwisolver ==1.4.5
Requires-Dist: markdown-it-py ==3.0.0
Requires-Dist: matplotlib ==3.8.2
Requires-Dist: mdurl ==0.1.2
Requires-Dist: networkx ==3.2.1
Requires-Dist: numpy ==1.26.3
Requires-Dist: packaging ==23.2
Requires-Dist: pillow ==10.2.0
Requires-Dist: pluggy ==1.4.0
Requires-Dist: Pygments ==2.17.2
Requires-Dist: pyparsing ==3.1.1
Requires-Dist: pytest ==8.0.0
Requires-Dist: python-dateutil ==2.8.2
Requires-Dist: rich ==13.7.0
Requires-Dist: setuptools ==68.2.2
Requires-Dist: six ==1.16.0
Requires-Dist: sqlitedict ==2.1.0
Requires-Dist: wheel ==0.41.2
